django_typed_perms/__init__.py
django_typed_perms/mixins.py
django_typed_perms/types.py
django_typed_perms/typing_utils.py
django_typed_perms-0.1.3.dist-info/METADATA
django_typed_perms-0.1.3.dist-info/WHEEL
django_typed_perms-0.1.3.dist-info/RECORD
