Metadata-Version: 2.4
Name: django-typed-perms
Version: 0.1.3
Summary: Typed Django permission checking
Project-URL: Homepage, https://github.com/leandrodesouzadev/django-typed-perms
Project-URL: Issues, https://github.com/leandrodesouzadev/django-typed-perms/issues
Author-email: Leandro de Souza <85115541+leandrodesouzadev@users.noreply.github.com>
Requires-Python: >=3.12
